simple_code/__init__.py
simple_code/add.py
simple_code/sub.py
simple_code/extras/__init__.py
simple_code/extras/div.py
simple_code/extras/mult.py
simple_code-0.0.1.dist-info/METADATA
simple_code-0.0.1.dist-info/WHEEL
simple_code-0.0.1.dist-info/top_level.txt
simple_code-0.0.1.dist-info/RECORD
